{
  "resources": [
    {
      "path": "data.csv",
      "name": "data",
      "profile": "tabular-data-resource",
      "scheme": "file",
      "format": "csv",
      "hashing": "md5",
      "encoding": "utf-8",
      "schema": {
        "fields": [
          {
            "name": "Parent Site",
            "type": "string",
            "constraints": {
              "enum": [
                "",
                "Abberd Brook",
                "Asham Wood Stream",
                "Bathford Brook",
                "Bitham Brook",
                "Bradley Brook",
                "Brinkworth Brook",
                "Bristol Avon Catchment",
                "Bristol Avon main river",
                "Broadmead Brook",
                "Buckland Brook",
                "By Brook main river",
                "Byde Mill Brook",
                "Cam Brook",
                "Charlton Stream",
                "Conygre Brook",
                "Doncombe Brook",
                "Easton Grey",
                "Easton Grey Gravel Replenishment",
                "Egford Brook",
                "Fisher's Brook",
                "Gauze Brook",
                "Hazel Brook",
                "Holt Stream",
                "Kilmersdon Brook",
                "Ladden Brook",
                "Lambrok Stream",
                "Lid Brook",
                "Luckington Brook",
                "Maiden Bradley Stream",
                "Main Bristol Frome",
                "Main Chalfield Brook",
                "Main Cowage Brook",
                "Main Midford Brook",
                "Main Newton Brook",
                "Main River Biss",
                "Main River Chew",
                "Main River Marden",
                "Main Semington Brook",
                "Main Somerset Frome",
                "Main Woodbridge Brook",
                "Mells River",
                "Mells Stream",
                "Milebourne Stream",
                "North Wraxall Brook",
                "Norton Brook",
                "Nunney Brook",
                "River Boyd",
                "River Somer",
                "River Trym",
                "River's Brook",
                "Rodbourne Brook",
                "Rodden Brook",
                "Sherston Avon",
                "Snails Brook",
                "St. Catherines Brook",
                "Stoke Brook",
                "Summerham Brook",
                "Tetbury Avon",
                "Wellow Brook",
                "Whatley Brook (Fordbury Water)",
                "Winford Brook"
              ]
            },
            "title": "Parent Site"
          },
          {
            "name": "Site",
            "type": "string",
            "constraints": {
              "enum": [
                "",
                "Abbey Farm",
                "Ashton Hill Farm",
                "Ashworthy Farm",
                "Back Bridge",
                "Baldham Farm",
                "Barton Country Park",
                "Blatchbridge (Te)",
                "Boyd Farm, Golden Valley (Coarse Sentinel)",
                "Brambles Farm (Se-02)",
                "Brinkworth",
                "Brokenborough  (Se-05)",
                "Brook End (Se-05)",
                "Brook House",
                "Buckland Dinham",
                "Bull's Bridge",
                "Byemills",
                "Calne Cement Works (Se-02)",
                "Calne STW (Te)",
                "Carriers Farm",
                "Castle Combe Golf Course (Se-02)",
                "Charlton",
                "Cherry Orchard",
                "Chew Magna",
                "Chewton Keynsham",
                "Chippenham (Te)",
                "Christian Malford (Te)",
                "Church Farm, Broughton Gifford",
                "Cleverton Road Bridge",
                "Cloford",
                "Cog Mill",
                "Coleford",
                "Colerne (Se-03)",
                "Coley",
                "Colts Green (Se-03)",
                "Combe Dingle lower",
                "Combe Dingle upper",
                "Combe Hay",
                "Compton Dando (Te)",
                "Court Farm, Wick",
                "Cow Bridge",
                "Cowick Farm (Se-02)",
                "Crab Mill",
                "Creamery (Te)",
                "D/S Calne",
                "D/S Chew Valley Lake (Te)",
                "D/S Of Camerton",
                "D/S Of Wellow",
                "D/S Rodbourne Road Bridge",
                "D/S Scutts Bridge (Te)",
                "D/S Stanton St Quintin",
                "D/s Bathford Paper mill",
                "D/s Home Farm",
                "D/s Hyam Farm",
                "Dalgety's",
                "Damsons Bridge (Te)",
                "Dead Woman's Bottom (Se-01)",
                "Dodington (Coombes end)",
                "Down Lane, Hullavington.",
                "Doynton",
                "Drewett's Mill",
                "Dunkerton (Se-04)",
                "Easton Grey Gravel Replenishment - Site 1",
                "Easton Grey Gravel Replenishment - Site 2",
                "Easton Grey Gravel Replenishment - Site 3",
                "Easton Town Bridge (Se-05)",
                "Eastville Park (Te)",
                "Edford Woods (Se-01)",
                "Fisher's Brook Cottages",
                "Fosse Way (Se-03)",
                "Fosseway (Se-03)",
                "Foxhills",
                "Frampton Cotterell",
                "Frenchay, Chapel Lane",
                "Frenchay, Flock Mill (Te)",
                "Gatcombe Mill",
                "Gatcombe Mill Brook",
                "Great Chalfield Manor",
                "Great Cheverell Mill",
                "Great Somerford (Te)",
                "Greenacres",
                "Hallatrow",
                "Hapsford House, d/s depleted reach",
                "Hapsford Mill, d/s tail race",
                "Hayle Farm (Se-02)",
                "Holt Manor",
                "Hookers Gate",
                "Horse Bridge (Te)",
                "Hullavington.",
                "Hurst Farm",
                "Iron Mill Farm (Se-03)",
                "Kendricks Farm",
                "Keynsham Park (Te)",
                "Kilmersdon",
                "Knights Farm",
                "Lacock (Te)",
                "Ladbrookside Farm",
                "Ladydown Mill",
                "Latteridge Pumping Station (Te)",
                "Littleton Mill (Se-04)",
                "Long Dean",
                "Longhouse Farm",
                "Lower Egford Farm",
                "Lower Shirehill Farm",
                "Lower Wraxall",
                "Luckington Court",
                "Manor Farm",
                "Meadowmead",
                "Melksham",
                "Merchants Farm",
                "Middlehill",
                "Midsomer Norton Sports Hall",
                "Mill Farm",
                "Mill Farm Bulkington",
                "Mill Hill",
                "Monkton Combe",
                "Mount Scylla Wood",
                "Murder Combe",
                "Nettleton Mill",
                "New Farm",
                "New House Farm",
                "New Leaze Farm",
                "Nibley (Se-03)",
                "Noah's Ark Pumping Station",
                "Norney Bridge",
                "North Wraxall",
                "Norton Stw",
                "Nunney STW (Se-01)",
                "Old Down Wood",
                "Old Hurst Farm (Se-01)",
                "Oldbury Court",
                "Oldford Farm",
                "Oxen Leaze Farm (Se-01)",
                "Paglinch Farm",
                "Pantry Bridge (Te)",
                "Penleigh Farm (Se-03)",
                "Pennsylvania Farm (Se-05)",
                "Penny Well",
                "Pensford (Te)",
                "Pinkney Mill",
                "Priston Mill (Se-05)",
                "Radford Mill",
                "Radstock",
                "Railford Bridge",
                "Railford Mill",
                "Ratford Bridge",
                "Rawlings Farm (Te)",
                "Riverside Gardens",
                "Road Bridge (Se-04)",
                "Rodbourne P.S.",
                "Rodbourne Road Bridge u/s",
                "Rodden Farm (Te)",
                "Rowde Mill (Se-01)",
                "Ruckley",
                "Scott's Mill",
                "Seend Bridge Farm",
                "Seven Acres",
                "Sherston Avon at Easton Grey - Site 1 Bottom Riffl",
                "Sherston Avon at Easton Grey - Site 2",
                "Sherston Avon at Easton Grey - Site 3",
                "Sherston Avon at Easton Grey - Site 4 Top Riffle",
                "Shoscombe",
                "Shrowl Bridge (Te)",
                "Siston Brook",
                "Slaughterford",
                "Snarlton Farm (Te)",
                "Somerford Bridge (Te)",
                "South Stoke",
                "Sprays Farm (Se-02)",
                "St Johns Park",
                "Stanley",
                "Stanton Drew (Te)",
                "Steanbridge Rd",
                "Stony Littleton",
                "Studley Green",
                "Sunset Hill",
                "Tanners Bridge",
                "Tellisford (Te06)",
                "Tellisford, Depleted Reach",
                "Temple Bridge (Se-04)",
                "Trench Lane",
                "Tubbs Elastics",
                "Tucking Mill (Se-04)",
                "Tuckson Wood",
                "Twinhoe",
                "U/S Cleeve Mill",
                "U/S Of Corston (Se-05)",
                "U/S West Kington",
                "U/S Yarn Brook",
                "U/s Waterside Farm",
                "Valley Farm",
                "Vernal Lodge",
                "Watley's End",
                "Weavern (Se-03)",
                "Welshmill",
                "Welton (Se-04)",
                "West Kington",
                "West Lavington (Se-01)",
                "Whaddon Grove Farm",
                "White Bridge",
                "Winterbourne (Te)",
                "Worton",
                "Wraxall Park Lower",
                "Wraxall Park Middle",
                "Wraxall Park Upper",
                "Wraxhall Park",
                "Writhlington",
                "d/s Fosse Way",
                "d/s Malmesbury bypass",
                "u/s Blackball Hatch (Te)",
                "u/s Brinkworth Bridge",
                "u/s Hyam Farm",
                "u/s Kingsmead Mill"
              ]
            },
            "title": "Site"
          },
          {
            "name": "Species",
            "type": "string",
            "constraints": {
              "enum": [
                "",
                "10-spined stickleback",
                "3-spined stickleback",
                "Atlantic salmon",
                "Barbel",
                "Bleak",
                "Brook lamprey",
                "Brook lamprey > ammocoete",
                "Brook lamprey ammocoetes",
                "Brown / sea trout",
                "Bullhead",
                "Chub",
                "Common [wild] carp",
                "Common bream",
                "Crucian carp",
                "Dace",
                "European eel",
                "European eels > elvers",
                "European elvers",
                "European glass eels",
                "Feral [brown] goldfish",
                "Flounder",
                "Goldfish varieties",
                "Grayling",
                "Gudgeon",
                "Lampetra sp.",
                "Lampetra sp. > ammocoete",
                "Lampetra sp. ammocoetes",
                "Lamprey sp.",
                "Lamprey sp. > ammocoete",
                "Lamprey sp. ammocoetes",
                "Minnow",
                "Perch",
                "Pike",
                "Rainbow trout",
                "Roach",
                "Roach x common bream hybrid",
                "Rudd",
                "Silver bream",
                "Stone loach",
                "Tench"
              ]
            },
            "title": "Species"
          },
          {
            "name": "Value",
            "type": "number",
            "title": "Value"
          },
          {
            "name": "Year",
            "type": "string",
            "title": "Year"
          }
        ]
      }
    }
  ],
  "profile": "data-package",
  "name": "14-4-1",
  "title": "Freshwater Fish Counts"
}