{"statuses":[{"value":"complete","translation_key":"complete"},{"value":"inprogress","translation_key":"inprogress"},{"value":"notstarted","translation_key":"notstarted"}],"overall":{"statuses":[{"status":"complete","translation_key":"complete","count":27,"percentage":11.02},{"status":"inprogress","translation_key":"inprogress","count":0,"percentage":0.0},{"status":"notstarted","translation_key":"notstarted","count":218,"percentage":88.98}],"totals":{"total":245}},"extra_fields":{},"goals":[{"goal":"1","statuses":[{"status":"complete","translation_key":"complete","count":2,"percentage":14.286},{"status":"inprogress","translation_key":"inprogress","count":0,"percentage":0.0},{"status":"notstarted","translation_key":"notstarted","count":12,"percentage":85.714}],"totals":{"total":14}},{"goal":"10","statuses":[{"status":"complete","translation_key":"complete","count":0,"percentage":0.0},{"status":"inprogress","translation_key":"inprogress","count":0,"percentage":0.0},{"status":"notstarted","translation_key":"notstarted","count":11,"percentage":100.0}],"totals":{"total":11}},{"goal":"11","statuses":[{"status":"complete","translation_key":"complete","count":1,"percentage":6.667},{"status":"inprogress","translation_key":"inprogress","count":0,"percentage":0.0},{"status":"notstarted","translation_key":"notstarted","count":14,"percentage":93.333}],"totals":{"total":15}},{"goal":"12","statuses":[{"status":"complete","translation_key":"complete","count":0,"percentage":0.0},{"status":"inprogress","translation_key":"inprogress","count":0,"percentage":0.0},{"status":"notstarted","translation_key":"notstarted","count":13,"percentage":100.0}],"totals":{"total":13}},{"goal":"13","statuses":[{"status":"complete","translation_key":"complete","count":0,"percentage":0.0},{"status":"inprogress","translation_key":"inprogress","count":0,"percentage":0.0},{"status":"notstarted","translation_key":"notstarted","count":8,"percentage":100.0}],"totals":{"total":8}},{"goal":"14","statuses":[{"status":"complete","translation_key":"complete","count":0,"percentage":0.0},{"status":"inprogress","translation_key":"inprogress","count":0,"percentage":0.0},{"status":"notstarted","translation_key":"notstarted","count":10,"percentage":100.0}],"totals":{"total":10}},{"goal":"15","statuses":[{"status":"complete","translation_key":"complete","count":0,"percentage":0.0},{"status":"inprogress","translation_key":"inprogress","count":0,"percentage":0.0},{"status":"notstarted","translation_key":"notstarted","count":14,"percentage":100.0}],"totals":{"total":14}},{"goal":"16","statuses":[{"status":"complete","translation_key":"complete","count":1,"percentage":4.348},{"status":"inprogress","translation_key":"inprogress","count":0,"percentage":0.0},{"status":"notstarted","translation_key":"notstarted","count":22,"percentage":95.652}],"totals":{"total":23}},{"goal":"17","statuses":[{"status":"complete","translation_key":"complete","count":1,"percentage":4.0},{"status":"inprogress","translation_key":"inprogress","count":0,"percentage":0.0},{"status":"notstarted","translation_key":"notstarted","count":24,"percentage":96.0}],"totals":{"total":25}},{"goal":"2","statuses":[{"status":"complete","translation_key":"complete","count":1,"percentage":7.692},{"status":"inprogress","translation_key":"inprogress","count":0,"percentage":0.0},{"status":"notstarted","translation_key":"notstarted","count":12,"percentage":92.308}],"totals":{"total":13}},{"goal":"3","statuses":[{"status":"complete","translation_key":"complete","count":10,"percentage":37.037},{"status":"inprogress","translation_key":"inprogress","count":0,"percentage":0.0},{"status":"notstarted","translation_key":"notstarted","count":17,"percentage":62.963}],"totals":{"total":27}},{"goal":"4","statuses":[{"status":"complete","translation_key":"complete","count":2,"percentage":18.182},{"status":"inprogress","translation_key":"inprogress","count":0,"percentage":0.0},{"status":"notstarted","translation_key":"notstarted","count":9,"percentage":81.818}],"totals":{"total":11}},{"goal":"5","statuses":[{"status":"complete","translation_key":"complete","count":2,"percentage":14.286},{"status":"inprogress","translation_key":"inprogress","count":0,"percentage":0.0},{"status":"notstarted","translation_key":"notstarted","count":12,"percentage":85.714}],"totals":{"total":14}},{"goal":"6","statuses":[{"status":"complete","translation_key":"complete","count":0,"percentage":0.0},{"status":"inprogress","translation_key":"inprogress","count":0,"percentage":0.0},{"status":"notstarted","translation_key":"notstarted","count":11,"percentage":100.0}],"totals":{"total":11}},{"goal":"7","statuses":[{"status":"complete","translation_key":"complete","count":2,"percentage":33.333},{"status":"inprogress","translation_key":"inprogress","count":0,"percentage":0.0},{"status":"notstarted","translation_key":"notstarted","count":4,"percentage":66.667}],"totals":{"total":6}},{"goal":"8","statuses":[{"status":"complete","translation_key":"complete","count":4,"percentage":23.529},{"status":"inprogress","translation_key":"inprogress","count":0,"percentage":0.0},{"status":"notstarted","translation_key":"notstarted","count":13,"percentage":76.471}],"totals":{"total":17}},{"goal":"9","statuses":[{"status":"complete","translation_key":"complete","count":1,"percentage":8.333},{"status":"inprogress","translation_key":"inprogress","count":0,"percentage":0.0},{"status":"notstarted","translation_key":"notstarted","count":11,"percentage":91.667}],"totals":{"total":12}},{"goal":"indicator_5","statuses":[{"status":"complete","translation_key":"complete","count":0,"percentage":0.0},{"status":"inprogress","translation_key":"inprogress","count":0,"percentage":0.0},{"status":"notstarted","translation_key":"notstarted","count":1,"percentage":100.0}],"totals":{"total":1}}]}