{"Year":["2017-18","2017-18","2017-18","2017-18","2017-18","2017-18","2017-18","2017-18","2017-18","2017-18","2017-18","2017-18","2017-18","2017-18","2017-18","2017-18","2017-18","2017-18","2017-18","2017-18","2017-18","2017-18","2017-18","2017-18","2017-18","2017-18","2017-18","2017-18","2017-18","2017-18","2017-18","2017-18","2017-18","2017-18","2017-18","2018-19","2018-19","2018-19","2018-19","2018-19","2018-19","2018-19","2018-19","2018-19","2018-19","2018-19","2018-19","2018-19","2018-19","2018-19","2018-19","2018-19","2018-19","2018-19","2018-19","2018-19","2018-19","2018-19","2018-19","2018-19","2018-19","2018-19","2018-19","2018-19","2018-19","2018-19","2018-19","2018-19","2018-19","2018-19","2019-20","2019-20","2019-20","2019-20","2019-20","2019-20","2019-20","2019-20","2019-20","2019-20","2019-20","2019-20","2019-20","2019-20","2019-20","2019-20","2019-20","2019-20","2019-20","2019-20","2019-20","2019-20","2019-20","2019-20","2019-20","2019-20","2019-20","2019-20","2019-20","2019-20","2019-20","2019-20","2019-20","2019-20","2019-20","2020-21","2020-21","2020-21","2020-21","2020-21","2020-21","2020-21","2020-21","2020-21","2020-21","2020-21","2020-21","2020-21","2020-21","2020-21","2020-21","2020-21","2020-21","2020-21","2020-21","2020-21","2020-21","2020-21","2020-21","2020-21","2020-21","2020-21","2020-21","2020-21","2020-21","2020-21","2020-21","2020-21","2020-21","2020-21","2017-18","2017-18","2018-19","2018-19","2019-20","2019-20","2020-21","2020-21"],"Series":["Ward","Ward","Ward","Ward","Ward","Ward","Ward","Ward","Ward","Ward","Ward","Ward","Ward","Ward","Ward","Ward","Ward","Ward","Ward","Ward","Ward","Ward","Ward","Ward","Ward","Ward","Ward","Ward","Ward","Ward","Ward","Ward","Ward","Ward","Ward","Ward","Ward","Ward","Ward","Ward","Ward","Ward","Ward","Ward","Ward","Ward","Ward","Ward","Ward","Ward","Ward","Ward","Ward","Ward","Ward","Ward","Ward","Ward","Ward","Ward","Ward","Ward","Ward","Ward","Ward","Ward","Ward","Ward","Ward","Ward","Ward","Ward","Ward","Ward","Ward","Ward","Ward","Ward","Ward","Ward","Ward","Ward","Ward","Ward","Ward","Ward","Ward","Ward","Ward","Ward","Ward","Ward","Ward","Ward","Ward","Ward","Ward","Ward","Ward","Ward","Ward","Ward","Ward","Ward","Ward","Ward","Ward","Ward","Ward","Ward","Ward","Ward","Ward","Ward","Ward","Ward","Ward","Ward","Ward","Ward","Ward","Ward","Ward","Ward","Ward","Ward","Ward","Ward","Ward","Ward","Ward","Ward","Ward","Ward","Ward","Ward","Ward","Ward","Ward","Ward","Deprivation","Deprivation","Deprivation","Deprivation","Deprivation","Deprivation","Deprivation","Deprivation"],"Deprivation decile":[null,null,null,null,null,null,null,null,null,null,null,null,null,null,null,null,null,null,null,null,null,null,null,null,null,null,null,null,null,null,null,null,null,null,null,null,null,null,null,null,null,null,null,null,null,null,null,null,null,null,null,null,null,null,null,null,null,null,null,null,null,null,null,null,null,null,null,null,null,null,null,null,null,null,null,null,null,null,null,null,null,null,null,null,null,null,null,null,null,null,null,null,null,null,null,null,null,null,null,null,null,null,null,null,null,null,null,null,null,null,null,null,null,null,null,null,null,null,null,null,null,null,null,null,null,null,null,null,null,null,null,null,null,null,null,null,null,null,null,null,"Most Deprived 10%","Least Deprived 10%","Least Deprived 10%","Most Deprived 10%","Most Deprived 10%","Least Deprived 10%","Least Deprived 10%","Most Deprived 10%"],"Ward":["Ashley","Easton","St George Troopers Hill","Avonmouth & Lawrence Weston","Knowle","St George West","Hartcliffe & Withywood","Brislington West","Clifton Down","Bishopston & Ashley Down","Westbury-on-Trym & Henleaze","Bedminster","Lockleaze","Windmill Hill","Stockwood","Hengrove & Whitchurch Park","Frome Vale","Bishopsworth","Brislington East",null,"Filwood","Hillfields","Southmead","Stoke Bishop","Henbury & Brentry","Central","St George Central","Eastville","Lawrence Hill","Horfield","Cotham","Southville","Redland","Clifton","Hotwells & Harbourside","Hengrove & Whitchurch Park","Easton","Frome Vale","Brislington West","Central","Hillfields","St George Central","St George West","Stoke Bishop","Redland","Southville","Stockwood","Henbury & Brentry","Lockleaze","Avonmouth & Lawrence Weston","Bishopsworth","Horfield","Southmead","Westbury-on-Trym & Henleaze","Ashley","Bedminster","Bishopston & Ashley Down","Clifton Down","Cotham","Filwood","Hotwells & Harbourside","Windmill Hill",null,"Brislington East","Clifton","Eastville","Hartcliffe & Withywood","Knowle","Lawrence Hill","St George Troopers Hill","Clifton Down","Ashley","Brislington East","Lockleaze","Redland","St George Central","Southville","Avonmouth & Lawrence Weston","Central","Cotham","Hengrove & Whitchurch Park","Stoke Bishop","Easton","Eastville","Hillfields","Horfield","Hotwells & Harbourside","St George Troopers Hill","Clifton","Filwood","Henbury & Brentry","Windmill Hill","Bedminster","Bishopston & Ashley Down","Bishopsworth","Brislington West","Frome Vale","Hartcliffe & Withywood","Knowle","Lawrence Hill","St George West","Southmead","Stockwood","Westbury-on-Trym & Henleaze",null,null,"Hillfields","Central","Redland","St George Troopers Hill","Southmead","Stockwood","Brislington East","Easton","Ashley","Brislington West","Hartcliffe & Withywood","Windmill Hill","Avonmouth & Lawrence Weston","Henbury & Brentry","Hengrove & Whitchurch Park","Hotwells & Harbourside","Westbury-on-Trym & Henleaze","Bedminster","Bishopsworth","Frome Vale","St George Central","St George West","Clifton","Cotham","Knowle","Lawrence Hill","Southville","Bishopston & Ashley Down","Clifton Down","Eastville","Filwood","Horfield","Lockleaze","Stoke Bishop",null,null,null,null,null,null,null,null],"GeoCode":["E05010885","E05010896","E05010911","E05010886","E05010906","E05010912","E05010900","E05010891","E05010894","E05010888","E05010917","E05010887","E05010908","E05010918","E05010915","E05010902","E05010899","E05010889","E05010890",null,"E05010898","E05010903","E05010913","E05010916","E05010901","E05010892","E05010910","E05010897","E05010907","E05010904","E05010895","E05010914","E05010909","E05010893","E05010905","E05010902","E05010896","E05010899","E05010891","E05010892","E05010903","E05010910","E05010912","E05010916","E05010909","E05010914","E05010915","E05010901","E05010908","E05010886","E05010889","E05010904","E05010913","E05010917","E05010885","E05010887","E05010888","E05010894","E05010895","E05010898","E05010905","E05010918",null,"E05010890","E05010893","E05010897","E05010900","E05010906","E05010907","E05010911","E05010894","E05010885","E05010890","E05010908","E05010909","E05010910","E05010914","E05010886","E05010892","E05010895","E05010902","E05010916","E05010896","E05010897","E05010903","E05010904","E05010905","E05010911","E05010893","E05010898","E05010901","E05010918","E05010887","E05010888","E05010889","E05010891","E05010899","E05010900","E05010906","E05010907","E05010912","E05010913","E05010915","E05010917",null,null,"E05010903","E05010892","E05010909","E05010911","E05010913","E05010915","E05010890","E05010896","E05010885","E05010891","E05010900","E05010918","E05010886","E05010901","E05010902","E05010905","E05010917","E05010887","E05010889","E05010899","E05010910","E05010912","E05010893","E05010895","E05010906","E05010907","E05010914","E05010888","E05010894","E05010897","E05010898","E05010904","E05010908","E05010916",null,null,null,null,null,null,null,null],"Value":[27.940444309,24.5296432276,25.3247350392,26.5651658136,32.3357775377,27.5294669855,20.8749794657,26.4383971328,23.0046639568,30.6537060612,31.7783701608,25.6351409629,15.2672881482,42.1106989309,7.2867041013,17.9986202978,16.6764929124,22.1013326423,18.3567505946,25.4947089315,32.8913066846,17.0236599986,24.722438605,30.452369017,19.8219665825,28.2314773156,11.5292304934,28.9450639291,30.9610819134,20.5738072613,31.1600096866,31.7312463779,29.4624181321,35.6946810033,19.9341330966,11.3609985199,22.3385367382,7.8487672493,11.6026609925,19.2160488338,15.982926004,17.0561642573,19.1288996648,24.920263103,16.2316862616,22.2447989458,14.6972448219,19.4128733791,22.2079597079,25.5496800592,8.2174449877,14.125013871,15.1984671214,23.650134947,21.3678976044,12.3700461032,16.0213057712,17.7319558642,21.7599021249,20.4574796386,18.7251775175,20.5707918204,17.5967619068,8.4565426755,18.1637913055,18.7166373262,11.9219328477,17.5438305994,17.4450305122,18.0408314091,13.8183712012,19.3847570781,10.8447721989,23.1142331354,21.3720690538,15.8033627247,18.5223435397,10.989688678,17.9072745752,27.1100874275,5.8895167952,21.082371157,17.567431666,18.1269098995,15.4039435065,19.9433148213,18.7474248733,27.5652724656,22.2840201901,15.2988053963,25.6529430288,21.3392424904,27.3314399113,17.9015933256,13.4516064117,13.1817978496,18.0788940757,12.7452119407,23.59553365,22.1789435047,21.2497323909,19.0012941238,7.0922758002,20.656160746,18.071524594,21.1201119755,17.3490987325,15.8077610299,29.4679584318,16.4369129378,16.8919111101,10.3650085941,11.7864259128,24.6422849893,30.9360078232,24.808993556,13.6676917716,26.4692190266,24.2307318867,24.4834632133,12.1697431768,14.805941324,28.6423518206,21.0290423797,16.7500260574,13.1909299202,19.590663998,21.7835118681,19.4713535927,30.9949597907,23.6940596386,16.9631428505,21.8460230441,31.7203670453,34.7698400628,20.4727048115,12.496975353,24.5457461221,25.2462472437,12.6815791596,23.853124358,27.8699517843,21.0163353319,16.9426597366,16.0171815532,17.657221147,26.8086565765,17.3249163505]}